chromotools/__init__.py
chromotools/module.py
chromotools/core/__init__.py
chromotools/utils/__init__.py
tests/__init__.py
tests/test_module.py
chromotools-0.1.2.dist-info/LICENSE
chromotools-0.1.2.dist-info/METADATA
chromotools-0.1.2.dist-info/WHEEL
chromotools-0.1.2.dist-info/top_level.txt
chromotools-0.1.2.dist-info/RECORD
