Metadata-Version: 2.1
Name: chromotools
Version: 0.1.2
Summary: Toolkit for chromosome segmentation, designed for advanced genetic analysis.
Home-page: https://github.com/daftar/chromotools
Author: Rodrigo J. R Santos
Author-email: contato@daftar.digital
License: UNKNOWN
Platform: UNKNOWN
Classifier: Programming Language :: Python :: 3
Classifier: License :: OSI Approved :: MIT License
Classifier: Operating System :: OS Independent
Requires-Python: >=3.8
